bluemumbai/__init__.py
bluemumbai/greetings.py
bluemumbai-0.3.dist-info/METADATA
bluemumbai-0.3.dist-info/WHEEL
bluemumbai-0.3.dist-info/top_level.txt
bluemumbai-0.3.dist-info/RECORD
