Metadata-Version: 2.1
Name: bluemumbai
Version: 0.3
Summary: Print and copy greetings based on user input for bluemumbai
Author: Your Name
Requires-Dist: pyperclip
